{
    "url": "https://defrafarming.blog.gov.uk/2021/11/11/meet-the-team-policy-adviser-emma-and-her-background-in-agriculture/",
    "title": "Meet the team: Policy Adviser Emma and her background in agriculture",
    "authors": [
        "Emma Bailey-Beech"
    ],
    "categories": [
        "environmental land management schemes",
        "Farmers in Defra",
        "Things we've learned"
    ],
    "pub_date": "2021-11-11T14:05:37+00:00",
    "content": [
        {
            "text": "In this post, I'd like to share how my background in agriculture led me to work in the Future Farming and Countryside Programme."
        },
        {
            "text": "My grandparents were farmers in Staffordshire,\u00a0but sadly\u00a0the farm was long gone by the time I came along.\u00a0Not being born directly into\u00a0farming\u00a0continues to be a source of disappointment to me!\u00a0"
        },
        {
            "text": "Although I was mostly brought up in a town, I spent\u00a0a lot of time\u00a0in the countryside. I\u00a0spent\u00a0weekends\u00a0feeding\u00a0the\u00a0lambs and calves at local farms. That soon turned into holiday\u00a0work milking cows. Once I was at\u00a0university, I\u00a0had holiday jobs lambing, harvesting, milking, and at the local abattoir.\u00a0"
        },
        {
            "heading": 3,
            "text": "Learning more about the thing I loved\u00a0"
        },
        {
            "text": "When I spoke to the careers adviser at school,\u00a0I remember feeling\u00a0excited that there were actual\u00a0agriculture colleges where I could\u00a0learn more about\u00a0what I loved.\u00a0"
        },
        {
            "text": "I signed up\u00a0for a\u00a0Youth Training Scheme (YTS)\u00a0which shows my age! I\u00a0was thrilled with my first wage of \u00a317.50 plus petrol money. It\u00a0covered\u00a0the 35-mile round journey to the tenanted dairy and chicken farm I\u2019d been placed on.\u00a0\u00a0"
        },
        {
            "text": "The YTS offered a terrific apprenticeship. The lecturer at\u00a0Rodbaston\u00a0College\u00a0was an excellent teacher and\u00a0had us doing all sorts of things.\u00a0\u00a0"
        },
        {
            "text": "Adding\u00a0this practical experience and entry level\u00a0agricultural\u00a0qualification\u00a0to my\u00a0good\u00a0GCSE results, I was accepted into\u00a0Harper Adams\u00a0\u2013 which just happened to be one of the biggest agricultural universities and my local \u2013\u00a0things were coming together!\u00a0\u00a0"
        },
        {
            "text": "My YTS had given me a love of pigs, so my degree was based\u00a0largely\u00a0around them.\u00a0My\u00a0dissertation\u00a0explored\u00a0pork eating quality. It\u00a0was sponsored by the local abattoir.\u00a0\u00a0"
        },
        {
            "heading": 3,
            "text": "Working with pigs\u00a0"
        },
        {
            "text": "I had always envisaged I\u2019d get a nice job on a pig farm once I\u2019d finished\u00a0university, but as some of you\u00a0might\u00a0recall,\u00a0the pig industry was\u00a0at the start of a massive\u00a0downturn\u00a0around 1998, so I needed to find something else.\u00a0"
        },
        {
            "text": "Being young and carefree was an advantage, as I\u00a0was happy to\u00a0be flexible. I\u00a0secured a\u00a0role as a meat inspector in the south-west.\u00a0"
        },
        {
            "text": "Given I\u2019d only just left university, I wasn\u2019t\u00a0fazed\u00a0by all the study and exams, and 9 months\u00a0later became a dual qualified meat inspector, which basically meant\u00a0I could\u00a0do\u00a0ante\u00a0and\u00a0post-mortems\u00a0on\u00a0any kind of animal\u00a0to\u00a0determine\u00a0if it was fit for the human food chain.\u00a0"
        },
        {
            "heading": 3,
            "text": "A move into policy"
        },
        {
            "text": "I\u00a0enjoyed this job, but there were few opportunities to progress, so when a pig\u00a0policy\u00a0job came up in\u00a0The Ministry of Agriculture, Fisheries and Food (MAFF), a precursor to Defra,\u00a0I jumped at the chance.\u00a0"
        },
        {
            "text": "I guess having a degree about\u00a0farm animals\u00a0helped, as I\u00a0thrived\u00a0and stayed in London for the next decade working on lots of different farm animal policy roles.\u00a0"
        },
        {
            "text": "In 2011 I was pregnant with my first child\u00a0and there was a restructure at work, so I left my post and\u00a0I\u00a0\u00a0moved to mid-Wales.\u00a0\u00a0"
        },
        {
            "text": "I then spent 4 years at\u00a0the\u00a0Agriculture and Horticulture Development Board\u00a0working on improving\u00a0pork safety. I spent\u00a0more time in abattoirs.\u00a0\u00a0"
        },
        {
            "text": "I then\u00a0worked\u00a0for a company that carried out traceability and welfare audits for a leading supermarket \u2013 the job was to review inspector\u2019s reports about farms all over the word and helping the clients remedy any non-conformances.\u00a0"
        },
        {
            "text": "I\u00a0loved reading about all the different practices on-farm and in abattoirs\u00a0and would have stayed there forever,\u00a0but sadly I was made redundant.\u00a0\u00a0"
        },
        {
            "text": "Fortunately,\u00a0Defra was taking on staff again to accommodate\u00a0the huge policy undertaking that occurred due to\u00a0Brexit, so in 2019 I\u00a0applied and got\u00a0back\u00a0in!\u00a0"
        },
        {
            "text": "I was keen to return to farming policy, and that\u2019s where I am now.\u00a0\u00a0"
        },
        {
            "heading": 3,
            "text": "The Sustainable Farming Incentive Pilot\u00a0"
        },
        {
            "text": "At the moment, I\u2019m working on the Sustainable Farming Incentive Pilot. Specifically, I\u2019m exploring how membership of environmental assurance schemes could help inform our risk profile for compliance or eligibility. I'm writing a separate blog post on that, so stay tuned!"
        },
        {
            "text": "The Sustainable Farming Incentive scheme is one of 3 schemes we\u2019re developing to encourage environmental land management. The other schemes are Local Nature Recovery and Landscape Recovery.\u00a0"
        },
        {
            "text": "It\u2019s\u00a0a fascinating\u00a0policy area that has the capacity to make a real difference on-farm.\u00a0"
        },
        {
            "text": "The scheme will reward farmers for managing their land in an environmentally sustainable way. The full scheme will launch in 2022, initially for farmers in England who\u00a0are eligible for\u00a0the Basic Payment Scheme (BPS).\u00a0"
        },
        {
            "text": "We\u2019ll be releasing more details about the Sustainable Farming Incentive at the end of this month, so do\u00a0subscribe to the blog\u00a0for an alert when we do.\u00a0\u00a0"
        },
        {
            "text": "There\u00a0are\u00a03\u00a0others with agricultural backgrounds\u00a0in my small team. It\u2019s nice to share stories and bring our experience to bear on policy decisions.\u00a0That\u2019s why I\u2019m so supportive of our co-design work, getting the views and opinions of farmers out there is so important if our plans are to work.\u00a0I\u00a0encourage\u00a0farmers and land managers to get in touch\u00a0and share their thoughts.\u00a0"
        },
        {
            "text": "Although I\u2019ll probably never live or work on a farm again,\u00a0I\u2019ve still had a most enjoyable career in agriculture\u00a0and am thrilled to be back in Defra\u00a0\u2013 long may\u00a0it\u00a0last!\u00a0"
        },
        {
            "text": "\u00a0"
        }
    ]
}