{
    "url": "https://defraenvironment.blog.gov.uk/2024/05/28/were-pausing-the-environment-blog/",
    "title": "We're pausing the Environment blog",
    "authors": [
        "Environment blog team"
    ],
    "categories": [
        "Uncategorized"
    ],
    "pub_date": "2024-05-28T14:13:28+01:00",
    "content": [
        {
            "text": "Last week, the Prime Minister announced that the General Election will be held on 4 July."
        },
        {
            "text": "As of 25 May, the Civil Service entered the pre-election period. This will last until the General Election concludes."
        },
        {
            "text": "During this time, there are restrictions on government activity - including communications. As a result, the Environment blog will be quieter than usual."
        },
        {
            "text": "We appreciate your ongoing engagement and thank you for your understanding. We'll be back as soon as possible."
        }
    ]
}