{
    "url": "https://homeofficemedia.blog.gov.uk/2025/05/31/latest-statement-in-response-to-small-boat-crossings/",
    "title": "Latest statement in response to small boat crossings",
    "authors": [
        "Home Office news team"
    ],
    "categories": [
        "Reactive statements"
    ],
    "pub_date": "2025-05-31T20:00:00+01:00",
    "content": [
        {
            "text": "A Home Office spokesperson said:\u201cWe all want to end dangerous small boat crossings, which threaten lives and undermine our border security.\u201cThe people-smuggling gangs do not care if the vulnerable people they exploit live or die, as long as they pay and we will stop at nothing to dismantle their business models and bring them to justice.\u201cThat is why this government has put together a serious plan to take down these networks at every stage.\u201cThrough international intelligence sharing under our Border Security Command, enhanced enforcement operations in Northern France and tougher legislation in the Border Security, Asylum and Immigration Bill, we are strengthening international partnerships and boosting our ability to identify, disrupt, and dismantle criminal gangs whilst strengthening the security of our borders.\""
        },
        {
            "text": "Background:"
        }
    ]
}