{
    "url": "https://teaching.blog.gov.uk/2026/02/23/the-value-of-transition/",
    "title": "The value of transition",
    "authors": [
        "Sarah Douglas"
    ],
    "categories": [
        "Inspiring teachers",
        "Pupil wellbeing and behaviour",
        "Secondary schools",
        "SEND"
    ],
    "pub_date": "2026-02-23T11:52:29+00:00",
    "content": [
        {
            "heading": 2,
            "text": "Why transition matters\u00a0"
        },
        {
            "text": "At Tanfield School,\u00a0we recognise the value of transition.\u00a0"
        },
        {
            "text": "Our Transition Model supports Year 6 students to prepare for a strong start\u00a0in\u00a0Year 7. Secondary school is a significant milestone in a young person's life, and a smooth transition sets the tone for\u00a0school life\u00a0and beyond.\u00a0"
        },
        {
            "heading": 2,
            "text": "Building relationships early\u00a0"
        },
        {
            "text": "Parents and carers begin to consider secondary school places as early as infancy.\u00a0We welcome families to our\u00a0open events\u00a0from\u00a0Year 4, which\u00a0helps\u00a0build essential relationships as we look forward to working together\u00a0with the child at the centre.\u00a0"
        },
        {
            "text": "Open events are enhanced by summer camps which develop familiarity. We have an\u00a0open-door\u00a0policy welcoming\u00a0families to visit at any time and see it in \u2018action\u2019... and why not a Friday afternoon? Standards\u00a0remain\u00a0high no matter\u00a0the\u00a0day of the week!\u00a0\u00a0"
        },
        {
            "heading": 2,
            "text": "Tailored support for individual needs\u00a0\u00a0"
        },
        {
            "text": "Early transition is common, especially for students\u00a0with\u00a0additional\u00a0needs and whose anxiety is heightened\u00a0by\u00a0change.\u00a0We set up the first visit and build upon this at the pace\u00a0that\u00a0suits the individual child. "
        },
        {
            "text": "These visits are bespoke and either the Year Manager or I\u00a0facilitate\u00a0them.\u00a0We\u2019ll\u00a0also attend Year 6 students\u2019 EHCP annual reviews before the end of the autumn term.\u00a0"
        },
        {
            "heading": 2,
            "text": "A familiar face for the journey\u00a0"
        },
        {
            "text": "The Year Manager plays a significant role in our pastoral support programme.\u00a0They\u2019re\u00a0non-teaching staff\u00a0who\u00a0are dedicated to following the students throughout their school journey.\u00a0\u00a0"
        },
        {
            "heading": 2,
            "text": "How we do it:\u00a0"
        },
        {
            "text": "Students often build an imagined picture of secondary school.\u00a0This is rarely a realistic one.\u00a0Our\u00a0Transition Model supports students to gain\u00a0first-hand\u00a0experience of school life.\u00a0"
        },
        {
            "heading": 2,
            "text": "Learning from primary partners\u00a0"
        },
        {
            "text": "As Transition Lead,\u00a0I\u00a0visit all our partner primary schools to speak with headteachers, SENDCos and Year 6 teachers. We recognise that the primary staff are the experts who have worked with\u00a0the\u00a0children for seven years.\u00a0\u00a0"
        },
        {
            "heading": 2,
            "text": "Getting the details right\u00a0"
        },
        {
            "text": "I build a picture of each student who may require an \u2018Individual Transition Plan\u2019.\u00a0This information is shared with colleagues back at Tanfield. "
        },
        {
            "text": "An Individual Transition Plan captures\u00a0a student's needs. This\u00a0can include the organisation of focus tools, sharing a\u00a0student's\u00a0likes and dislikes, a need for\u00a0a Chromebook\u00a0and/or coloured paper, dietary requirements, medical needs, SATs concessions and\u00a0additional\u00a0literacy and numeracy interventions through access to our nurture class.\u00a0"
        },
        {
            "heading": 2,
            "text": "Small adaptations,\u00a0big difference\u00a0\u00a0"
        },
        {
            "text": "Successful transition is a team effort.\u00a0I know that our partner primary headteachers really appreciate our transition programme and feel confident about their students moving on.\u00a0"
        },
        {
            "text": "We are successful because we are invested in the future of our students. As our mission statement affirms - \u2018we want all students to attend the best universities or real alternatives and thrive in all aspects of their life\u2019.\u00a0"
        },
        {
            "text": "Does it take a lot of time and dedication? Yes.\u00a0\u00a0"
        },
        {
            "text": "Is it worth it? Absolutely.\u00a0"
        }
    ]
}