{
    "url": "https://healthmedia.blog.gov.uk/2025/07/14/what-the-10-year-health-plan-means-for-you/",
    "title": "What the 10 Year Health Plan means for you",
    "authors": [
        "ttowers"
    ],
    "categories": [
        "NHS",
        "Public Health"
    ],
    "pub_date": "2025-07-14T15:05:14+01:00",
    "content": [
        {
            "heading": 2,
            "text": "PatientsSummary"
        },
        {
            "text": "Our health system is in crisis. If we don\u2019t act now, we risk the NHS ceasing to exist as a publicly funded service, free at the point of use."
        },
        {
            "text": "But if we seize the opportunities provided by new technology, medicines, and innovation, then we can deliver better care for all patients - no matter where they live or how much they earn - and better value for taxpayers."
        },
        {
            "text": "Our 10 Year Health Plan, backed by \u00a329b, will get the NHS back on its feet and to make it fit for the future."
        },
        {
            "text": "Here's what we're doing: "
        },
        {
            "text": "From hospital to community"
        },
        {
            "text": "From analogue to digital"
        },
        {
            "text": "From sickness to prevention"
        }
    ]
}