{
    "url": "https://defrafarming.blog.gov.uk/2023/01/23/slurry-infrastructure-grant-time-to-apply/",
    "title": "Slurry Infrastructure grant: time to apply",
    "authors": [
        "Thomas Proudfoot"
    ],
    "categories": [
        "Payments for equipment, technology and infrastructure"
    ],
    "pub_date": "2023-01-23T10:29:00+00:00",
    "content": [
        {
            "text": "At the end of this month, the first round of the Slurry Infrastructure grant will close for applications. So, if you haven\u2019t yet applied, now is the time to.\u00a0"
        },
        {
            "text": "In this post, I\u2019ll give you a recap of the grant and the process to apply before 31 January.\u00a0"
        },
        {
            "heading": 2,
            "text": "The Slurry Infrastructure grant\u00a0"
        },
        {
            "text": "The Slurry Infrastructure grant is designed to help you improve or expand your slurry storage capacity to 6 months and improve the use of organic nutrients on your farm.\u00a0"
        },
        {
            "text": "You can use the grant to pay for:\u00a0"
        },
        {
            "text": "You can use the grant to replace stores that are no longer fit-for-purpose, build additional storage or expand an existing store."
        },
        {
            "text": " The grant will also contribute towards the costs of impermeable covers and supporting equipment.\u00a0"
        },
        {
            "text": "The minimum grant you can apply for is \u00a325,000. The maximum grant is \u00a3250,000 for each applicant business."
        },
        {
            "heading": 2,
            "text": "Applying for a Slurry Infrastructure grant\u00a0"
        },
        {
            "heading": 3,
            "text": "Step 1: Take a look at the guidance"
        },
        {
            "text": "The full Slurry Infrastructure grant guidance can be found on GOV.UK."
        },
        {
            "text": " It sets out:"
        },
        {
            "text": "Last month, we held a webinar to discuss the grant. I'll embed the view below."
        },
        {
            "text": "I\u2019ve also blogged about the grant before. If you click on my name at the top of this page, you\u2019ll see my previous posts."
        },
        {
            "heading": 3,
            "text": "Step 2: Use the online checker\u00a0"
        },
        {
            "text": "The first part of the application process is an online checker.\u202fYou\u2019ll find it on the\u202fSlurry Infrastructure grant page on GOV.UK.\u202f"
        },
        {
            "text": "It's important to be accurate about your slurry storage needs and project plans.\u202f"
        },
        {
            "text": "The Rural Payments Agency (RPA)\u202fand the\u202fEnvironment Agency\u202fcreated guidance to help you\u202fplan your slurry storage.\u202f"
        },
        {
            "heading": 3,
            "text": "Step 3: Assessment\u00a0"
        },
        {
            "text": "Once the online checker closes, the RPA will\u202flook at how many projects can be funded.\u00a0"
        },
        {
            "text": "If the scheme is oversubscribed, the RPA will identify the applications with a higher environmental benefit. This will be based on the priority areas shown in\u202fMAGIC.\u00a0"
        },
        {
            "text": "This will be based on location and proximity to areas where action is most needed to reduce pollution from agriculture."
        },
        {
            "text": "You can read about how we\u2019ll do this in detail.\u202f"
        },
        {
            "heading": 3,
            "text": "Step 4: Full application"
        },
        {
            "text": "If you are invited to make a full application, you will be asked further questions about your project.\u00a0"
        },
        {
            "text": "It's important that you don\u2019t start your project until your grant funding agreement is in place."
        },
        {
            "text": "You can certainly get quotes and apply for planning permission, but you cannot pay for any eligible items or start construction.\u00a0"
        },
        {
            "heading": 2,
            "text": "Coming up"
        },
        {
            "text": "I'll explain how we completed the shortlisting after the checker closes, so do subscribe to the blog.\u00a0"
        }
    ]
}