{
    "url": "https://defraenvironment.blog.gov.uk/2023/11/29/biodiversity-net-gain-guidance-what-you-need-to-know/",
    "title": "Biodiversity net gain guidance \u2013 what you need to know",
    "authors": [
        "Land Use Policy Team"
    ],
    "categories": [
        "Biodiversity Net Gain",
        "Land Use"
    ],
    "pub_date": "2023-11-29T17:14:10+00:00",
    "content": [
        {
            "text": "We are pleased to announce the publication of step-by-step guidance taking you through the biodiversity net gain process."
        },
        {
            "text": "The guidance drafting process has been a truly collaborative effort, involving a range of government departments and ALBs such as Natural England, Forestry Commission, and the Environment Agency."
        },
        {
            "text": "We are very grateful to the multiple stakeholders who we frequently engaged and consulted with to ensure guidance works best for users."
        },
        {
            "text": "Defra guidance"
        },
        {
            "text": "Defra guidance covers the following BNG areas:"
        },
        {
            "text": "Further guidance"
        },
        {
            "text": "DLUHC have also provided draft BNG planning practice guidance here: Draft biodiversity net gain planning practice guidance - GOV.UK (www.gov.uk) \u00a0DLUHC guidance covers further legal and technical aspects of BNG, including guidance on the planning process, phased development, enforcement and more."
        },
        {
            "text": "Feedback"
        },
        {
            "text": "We welcome feedback on the guidance, particularly in the run up to BNG coming into force. Please find a survey linked to each guidance page."
        }
    ]
}