{
    "url": "https://educationhub.blog.gov.uk/2022/10/20/how-to-help-your-childs-early-language-skills-top-ten-tips-from-the-experts/",
    "title": "How to help your child's early language skills - top ten tips from the experts",
    "authors": [
        "Media Officer"
    ],
    "categories": [
        "Babies",
        "early years",
        "Home Learning Environment"
    ],
    "pub_date": "2022-10-20T13:03:07+01:00",
    "content": [
        {
            "text": "Your child\u2019s education starts at home long before they enter the classroom. And even when they start nursery or school the home is where a significant amount of their learning happens."
        },
        {
            "text": "That\u2019s why it\u2019s really important to build a positive learning environment at home \u2013 so parents can bring learning moments into their everyday activities while their child enjoys stimulating and engaging activity."
        },
        {
            "text": "Creating an environment at home that actively encourages children to develop their language and social skills provides a great foundation for more formal learning.. And developing language skills at a young age is consistently linked with better school attainment and job prospects."
        },
        {
            "text": "Tracy Jackson, Head of Early Years at the National Literacy Trust, and Dr Kirsten Asmussen, Head of Child Development and Early Intervention Foundation have some top tips on how you can build a great home learning environment and help your child express themselves in their earliest years:"
        },
        {
            "text": "Babies"
        },
        {
            "text": "\u00a0"
        },
        {
            "text": "\u00a0"
        },
        {
            "text": "\u00a0"
        },
        {
            "text": "\u00a0"
        },
        {
            "text": "\u00a0"
        },
        {
            "text": "Young Children"
        },
        {
            "text": "\u00a0"
        },
        {
            "text": "\u00a0"
        },
        {
            "text": "\u00a0"
        },
        {
            "text": "\u00a0"
        },
        {
            "text": "\u00a0"
        },
        {
            "text": "Every child is different and there\u2019s no one-size-fits-all. What matters most is spending time with your child chatting, playing, and reading. Every little thing you do with them will set them up well as keen little learners for when they start school."
        },
        {
            "text": "For more information visit \u2018Start for Life \u2013 chat, play, read\u2019 where you can find tips and activities to help support your child's development and find further support in your local area."
        }
    ]
}